math_tools_v3_0/.ipynb_checkpoints/__init__-checkpoint.py
math_tools_v3_0/.ipynb_checkpoints/cli-checkpoint.py
math_tools_v3_0/.ipynb_checkpoints/service-checkpoint.py
math_tools_v3_0/.ipynb_checkpoints/test_service-checkpoint.py
math_tools_v3_0/.ipynb_checkpoints/ultra_simple_test-checkpoint.py
math_tools_v3_0/__init__.py
math_tools_v3_0/cli.py
math_tools_v3_0/service.py
math_tools_v3_0/test_service.py
math_tools_v3_0/ultra_simple_test.py
math_tools_v3_0-0.17.0.dist-info/WHEEL
math_tools_v3_0-0.17.0.dist-info/entry_points.txt
math_tools_v3_0-0.17.0.dist-info/METADATA
math_tools_v3_0-0.17.0.dist-info/RECORD
