Metadata-Version: 2.3
Name: math-tools-v3-0
Version: 0.17.0
Summary: Add your description here
Requires-Dist: mcp>=1.0.0
Requires-Python: >=3.10
